ragify/__init__.py
ragify/py.typed
ragify-0.1.0.dist-info/METADATA
ragify-0.1.0.dist-info/WHEEL
ragify-0.1.0.dist-info/licenses/LICENSE.md
ragify-0.1.0.dist-info/RECORD
